<?xml version="1.0" encoding="UTF-8"?>
<objects serializationModel="Studio.01.10.00">
    <object class="AudioFile" id="{64453db0-8d50-4fa9-8564-3db6b54f56d3}">
        <property name="assetPath">
            <value>stepCarpet01.wav</value>
        </property>
        <property name="frequencyInKHz">
            <value>44.0999985</value>
        </property>
        <property name="channelCount">
            <value>2</value>
        </property>
        <property name="length">
            <value>0.9049206349206349</value>
        </property>
        <relationship name="masterAssetFolder">
            <destination>{5e33648b-59db-4362-be37-9eb28d6ebdbc}</destination>
        </relationship>
    </object>
</objects>
